[
    {
        "NOME_FARMACO": "'Integratore ingresso bovino'",
        "ETICHETTA_ANIMALE": "'0000000001'",
        "DATA_VISITA": "DATE '2025-02-26'",
        "NOME_PRODOTTO": "'Integratore vitaminico veterinario'",
        "UNITA_MISURA": "'mL'",
        "DURATA_GIORNI": 5,
        "QUANTITA_GIORNALIERA": 20.0
    },
    {
        "NOME_FARMACO": "'Terapia pollame biosicurezza'",
        "ETICHETTA_ANIMALE": "'0000000036'",
        "DATA_VISITA": "DATE '2025-03-10'",
        "NOME_PRODOTTO": "'Antibiotico veterinario pollame'",
        "UNITA_MISURA": "'mL'",
        "DURATA_GIORNI": 7,
        "QUANTITA_GIORNALIERA": 0.5
    }
]